Heimdall/__about__.py
Heimdall/cell_representations.py
Heimdall/datasets.py
Heimdall/embedding.py
Heimdall/fc.py
Heimdall/fe.py
Heimdall/fg.py
Heimdall/flash_attention_models.py
Heimdall/losses.py
Heimdall/order.py
Heimdall/reduce.py
Heimdall/tailor.py
Heimdall/trainer.py
Heimdall/utils.py
sc_heimdall-2.2.0.dist-info/METADATA
sc_heimdall-2.2.0.dist-info/WHEEL
sc_heimdall-2.2.0.dist-info/licenses/LICENSE
sc_heimdall-2.2.0.dist-info/RECORD
