Metadata-Version: 2.4
Name: sc-heimdall
Version: 2.2.0
Summary: Heimdall: A Comprehensive Paradigm for Evaluating Single-Cell Representations within Foundational Models
Author: Remy Liu, Nicholas Ho
Author-email: Shahul Alam <alam.shahul@gmail.com>
License: MIT License
License-File: LICENSE
Classifier: License :: OSI Approved :: MIT License
Classifier: Operating System :: OS Independent
Classifier: Programming Language :: Python :: 3
Requires-Python: >=3.10
Requires-Dist: accelerate
Requires-Dist: anndata>=0.11.0
Requires-Dist: awkward
Requires-Dist: datasets
Requires-Dist: einops
Requires-Dist: hydra-core
Requires-Dist: mygene
Requires-Dist: numpy
Requires-Dist: omegaconf
Requires-Dist: packaging
Requires-Dist: pandas
Requires-Dist: scanpy
Requires-Dist: scikit-learn
Requires-Dist: scipy
Requires-Dist: torchmetrics
Requires-Dist: tqdm
Requires-Dist: transformers
Requires-Dist: wandb
